{"is_source_file": true, "format": "Python", "description": "This file implements an interactive SQLite database shell tailored for a streaming database project, allowing users to run SQL commands and perform database inspections such as listing tables, showing schemas, and describing tables.", "external_files": ["sqlite3"], "external_methods": ["sqlite3.connect", "sqlite3.Error"], "published": ["main", "list_tables", "show_schema", "describe_table", "execute_query", "print_help"], "classes": [], "methods": [{"name": "print_help()", "description": "Prints help information about available commands in the shell.", "scope": "", "scopeKind": ""}, {"name": "list_tables(cursor)", "description": "Lists all user-defined tables in the SQLite database.", "scope": "", "scopeKind": ""}, {"name": "show_schema(cursor, table_name=None)", "description": "Displays CREATE statements for specific or all tables.", "scope": "", "scopeKind": ""}, {"name": "describe_table(cursor, table_name)", "description": "Shows detailed structure of a specific table.", "scope": "", "scopeKind": ""}, {"name": "execute_query(cursor, query)", "description": "Executes a given SQL query and displays results or affected rows.", "scope": "", "scopeKind": ""}, {"name": "main()", "description": "Main loop running the interactive shell, handling user input and interactions.", "scope": "", "scopeKind": ""}], "calls": ["sqlite3.connect", "sqlite3.Error", "cursor.execute", "cursor.fetchall", "cursor.description", "sys.exit", "print", "input"], "search-terms": ["sqlite_shell", "interactive shell", "database commands", "SQLite", "streaming_database", "db_shell.py", "SQL command parser"], "state": 2, "file_id": 9, "knowledge_revision": 19, "git_revision": "db23b0da2c0d25e921a10c7076a57447c81e1913", "ctags": [{"_type": "tag", "name": "DB_NAME", "path": "/home/kavia/workspace/code-generation/streamline-video-platform-221764-221776/streaming_database/db_shell.py", "pattern": "/^DB_NAME = \"myapp.db\"$/", "language": "Python", "kind": "variable"}, {"_type": "tag", "name": "describe_table", "path": "/home/kavia/workspace/code-generation/streamline-video-platform-221764-221776/streaming_database/db_shell.py", "pattern": "/^def describe_table(cursor, table_name):$/", "language": "Python", "kind": "function", "signature": "(cursor, table_name)"}, {"_type": "tag", "name": "execute_query", "path": "/home/kavia/workspace/code-generation/streamline-video-platform-221764-221776/streaming_database/db_shell.py", "pattern": "/^def execute_query(cursor, query):$/", "language": "Python", "kind": "function", "signature": "(cursor, query)"}, {"_type": "tag", "name": "list_tables", "path": "/home/kavia/workspace/code-generation/streamline-video-platform-221764-221776/streaming_database/db_shell.py", "pattern": "/^def list_tables(cursor):$/", "language": "Python", "kind": "function", "signature": "(cursor)"}, {"_type": "tag", "name": "main", "path": "/home/kavia/workspace/code-generation/streamline-video-platform-221764-221776/streaming_database/db_shell.py", "pattern": "/^def main():$/", "language": "Python", "kind": "function", "signature": "()"}, {"_type": "tag", "name": "print_help", "path": "/home/kavia/workspace/code-generation/streamline-video-platform-221764-221776/streaming_database/db_shell.py", "pattern": "/^def print_help():$/", "language": "Python", "kind": "function", "signature": "()"}, {"_type": "tag", "name": "show_schema", "path": "/home/kavia/workspace/code-generation/streamline-video-platform-221764-221776/streaming_database/db_shell.py", "pattern": "/^def show_schema(cursor, table_name=None):$/", "language": "Python", "kind": "function", "signature": "(cursor, table_name=None)"}], "hash": "49a5803c07b5775772878889145d3bed", "format-version": 4, "code-base-name": "streaming_database", "filename": "streaming_database/db_shell.py", "fields": [{"name": "DB_NAME = \"myapp.db\"", "scope": "", "scopeKind": "", "description": "unavailable"}], "revision_history": [{"19": "db23b0da2c0d25e921a10c7076a57447c81e1913"}]}